<?xml version="1.0" encoding="UTF-8"?><record_update table="sp_row">
    <sp_row action="INSERT_OR_UPDATE">
        <class_name/>
        <order>1</order>
        <sp_column/>
        <sp_container display_value="IT Health - Device X-Ray - Container 2">a59e6d311b7329509b7d32231b4bcbcb</sp_container>
        <sys_class_name>sp_row</sys_class_name>
        <sys_created_by>andre.nunes@stefanini.com</sys_created_by>
        <sys_created_on>2023-07-03 16:33:21</sys_created_on>
        <sys_id>259e25711b7329509b7d32231b4bcb2b</sys_id>
        <sys_mod_count>0</sys_mod_count>
        <sys_name>1</sys_name>
        <sys_package display_value="Chameleon" source="x_stefa_chameleon">15b425181b832510cc28c955624bcbd6</sys_package>
        <sys_policy/>
        <sys_scope display_value="Chameleon">15b425181b832510cc28c955624bcbd6</sys_scope>
        <sys_update_name>sp_row_259e25711b7329509b7d32231b4bcb2b</sys_update_name>
        <sys_updated_by>andre.nunes@stefanini.com</sys_updated_by>
        <sys_updated_on>2023-07-03 16:33:21</sys_updated_on>
    </sp_row>
</record_update>
