<?xml version="1.0" encoding="UTF-8"?><record_update sys_domain="global" table="x_stefa_persona_ba_persona_criteria">
    <x_stefa_persona_ba_persona_criteria action="INSERT_OR_UPDATE">
        <active>true</active>
        <advanced>true</advanced>
        <company/>
        <department/>
        <group/>
        <location/>
        <match_all>false</match_all>
        <name>Persona for IT</name>
        <persona>b9b461171bfee5109b7d32231b4bcb1f</persona>
        <role/>
        <script><![CDATA[var strArr = "b9b461171bfee5109b7d32231b4bcb1f"; 
answer = new x_stefa_persona_ba.utilPersonas().arePersonas(user_id, strArr);]]></script>
        <short_description/>
        <sys_class_name>x_stefa_persona_ba_persona_criteria</sys_class_name>
        <sys_created_by>vinicius.lourenco@stefanini.com</sys_created_by>
        <sys_created_on>2023-06-13 21:02:31</sys_created_on>
        <sys_domain>global</sys_domain>
        <sys_domain_path>/</sys_domain_path>
        <sys_id>be4e5a7552934ce0acbffa087edf400a</sys_id>
        <sys_mod_count>0</sys_mod_count>
        <sys_name>Persona for IT</sys_name>
        <sys_package display_value="Chameleon" source="x_stefa_chameleon">15b425181b832510cc28c955624bcbd6</sys_package>
        <sys_policy/>
        <sys_scope display_value="Chameleon">15b425181b832510cc28c955624bcbd6</sys_scope>
        <sys_update_name>x_stefa_persona_ba_persona_criteria_be4e5a7552934ce0acbffa087edf400a</sys_update_name>
        <sys_updated_by>vinicius.lourenco@stefanini.com</sys_updated_by>
        <sys_updated_on>2023-06-13 21:02:31</sys_updated_on>
        <user/>
    </x_stefa_persona_ba_persona_criteria>
    <sys_translated_text action="delete_multiple" query="documentkey=be4e5a7552934ce0acbffa087edf400a"/>
</record_update>
